nonebot_plugin_time_card/__init__.py
nonebot_plugin_time_card/config.py
nonebot_plugin_time_card-1.0.11.dist-info/licenses/LICENSE
nonebot_plugin_time_card-1.0.11.dist-info/METADATA
nonebot_plugin_time_card-1.0.11.dist-info/WHEEL
nonebot_plugin_time_card-1.0.11.dist-info/entry_points.txt
nonebot_plugin_time_card-1.0.11.dist-info/top_level.txt
nonebot_plugin_time_card-1.0.11.dist-info/RECORD
