Metadata-Version: 2.4
Name: nonebot-plugin-time-card
Version: 1.0.11
Summary: Nonebot 2.4.3 插件：自动更新机器人群聊昵称并显示实时时间，支持超级管理员开关与热重载
Author-email: meng <mengde_email@163.com>
License-Expression: MIT
Project-URL: Homepage, https://github.com/MengdeUser/nonebot-plugin-time-card
Project-URL: Issue Tracker, https://github.com/MengdeUser/nonebot-plugin-time-card/issues
Project-URL: Documentation, https://github.com/MengdeUser/nonebot-plugin-time-card/blob/master/README.md
Keywords: nonebot2,nonebot-plugin,qqbot,time-card
Classifier: Programming Language :: Python :: 3
Classifier: Programming Language :: Python :: 3.8
Classifier: Programming Language :: Python :: 3.9
Classifier: Programming Language :: Python :: 3.10
Classifier: Programming Language :: Python :: 3.11
Classifier: Programming Language :: Python :: 3.12
Classifier: Operating System :: OS Independent
Classifier: Intended Audience :: Developers
Classifier: Topic :: Software Development :: Libraries :: Python Modules
Classifier: Topic :: Communications :: Chat
Classifier: Topic :: Utilities
Requires-Python: >=3.8
License-File: LICENSE
Requires-Dist: nonebot2<3.0.0,>=2.4.3
Requires-Dist: nonebot-adapter-onebot<3.0.0,>=2.2.0
Dynamic: license-file
